dacite/__init__.py
dacite/config.py
dacite/core.py
dacite/data.py
dacite/dataclasses.py
dacite/exceptions.py
dacite/py.typed
dacite/types.py
dacite1-1.6.99.dist-info/LICENSE
dacite1-1.6.99.dist-info/METADATA
dacite1-1.6.99.dist-info/WHEEL
dacite1-1.6.99.dist-info/top_level.txt
dacite1-1.6.99.dist-info/RECORD
